{
  "id": "7750a413c93741049eb06af4039fc98c",
  "price": {
    "totalPaymentPrice": {
      "paymentCurrencyAmount": 5280,
      "paymentCurrencyCode": "RUB",
      "paymentCurrencyExchangeRate": 1,
      "paymentCurrencySymbol": "₽"
    },
    "totalPrice": {
      "basePayoutCurrencyCode": "USD",
      "basePayoutPrice": 70,
      "convenienceFee": 0,
      "currencyCode": "RUB",
      "discount": 1320,
      "discountPrice": 5280,
      "originalPrice": 6600,
      "originalUnitPrice": null,
      "unitPrice": null,
      "vat": 0,
      "voucherDiscount": 0
    }
  }
}