{
  "id": "39859de84b3f4f7f8fa1f5a44edf4e29",
  "price": {
    "totalPaymentPrice": {
      "paymentCurrencyAmount": 24999,
      "paymentCurrencyCode": "SAR",
      "paymentCurrencyExchangeRate": 1,
      "paymentCurrencySymbol": "ر.س"
    },
    "totalPrice": {
      "basePayoutCurrencyCode": "USD",
      "basePayoutPrice": 5797,
      "convenienceFee": 0,
      "currencyCode": "SAR",
      "discount": 0,
      "discountPrice": 24999,
      "originalPrice": 24999,
      "originalUnitPrice": null,
      "unitPrice": null,
      "vat": 3261,
      "voucherDiscount": 0
    }
  }
}