{
  "id": "bfdbe8b8e105460eae19c664e51b95cb",
  "price": {
    "totalPaymentPrice": {
      "paymentCurrencyAmount": 566,
      "paymentCurrencyCode": "SAR",
      "paymentCurrencyExchangeRate": 1,
      "paymentCurrencySymbol": "ر.س"
    },
    "totalPrice": {
      "basePayoutCurrencyCode": "USD",
      "basePayoutPrice": 131,
      "convenienceFee": 0,
      "currencyCode": "SAR",
      "discount": 63,
      "discountPrice": 566,
      "originalPrice": 629,
      "originalUnitPrice": null,
      "unitPrice": null,
      "vat": 74,
      "voucherDiscount": 0
    }
  }
}