{
  "id": "2e4e9ce2c17649018d45692284dfd890",
  "price": {
    "totalPaymentPrice": {
      "paymentCurrencyAmount": 3540,
      "paymentCurrencyCode": "TRY",
      "paymentCurrencyExchangeRate": 1,
      "paymentCurrencySymbol": "₺"
    },
    "totalPrice": {
      "basePayoutCurrencyCode": "USD",
      "basePayoutPrice": 369,
      "convenienceFee": 0,
      "currencyCode": "TRY",
      "discount": 2360,
      "discountPrice": 3540,
      "originalPrice": 5900,
      "originalUnitPrice": null,
      "unitPrice": null,
      "vat": 540,
      "voucherDiscount": 0
    }
  }
}