{
  "id": "9aa227e2ba294bb1a95c95fde892eb31",
  "price": {
    "totalPaymentPrice": {
      "paymentCurrencyAmount": 1250,
      "paymentCurrencyCode": "TRY",
      "paymentCurrencyExchangeRate": 1,
      "paymentCurrencySymbol": "₺"
    },
    "totalPrice": {
      "basePayoutCurrencyCode": "USD",
      "basePayoutPrice": 123,
      "convenienceFee": 0,
      "currencyCode": "TRY",
      "discount": 1250,
      "discountPrice": 1250,
      "originalPrice": 2500,
      "originalUnitPrice": null,
      "unitPrice": null,
      "vat": 191,
      "voucherDiscount": 0
    }
  }
}