{
  "id": "12dddd5aa7e0479b8dce43d26c71abe0",
  "price": {
    "totalPaymentPrice": {
      "paymentCurrencyAmount": 699,
      "paymentCurrencyCode": "CHF",
      "paymentCurrencyExchangeRate": 1,
      "paymentCurrencySymbol": "Fr."
    },
    "totalPrice": {
      "basePayoutCurrencyCode": "USD",
      "basePayoutPrice": 701,
      "convenienceFee": 0,
      "currencyCode": "CHF",
      "discount": 0,
      "discountPrice": 699,
      "originalPrice": 699,
      "originalUnitPrice": null,
      "unitPrice": null,
      "vat": 50,
      "voucherDiscount": 0
    }
  }
}