{
  "id": "1a29e88117594fe3804916220174b1ae",
  "price": {
    "totalPaymentPrice": {
      "paymentCurrencyAmount": 279,
      "paymentCurrencyCode": "CHF",
      "paymentCurrencyExchangeRate": 1,
      "paymentCurrencySymbol": "Fr."
    },
    "totalPrice": {
      "basePayoutCurrencyCode": "USD",
      "basePayoutPrice": 287,
      "convenienceFee": 0,
      "currencyCode": "CHF",
      "discount": 120,
      "discountPrice": 279,
      "originalPrice": 399,
      "originalUnitPrice": null,
      "unitPrice": null,
      "vat": 20,
      "voucherDiscount": 0
    }
  }
}