{
  "id": "423f71d9b14a4d55bd792ee425adc43b",
  "price": {
    "totalPaymentPrice": {
      "paymentCurrencyAmount": 199,
      "paymentCurrencyCode": "CHF",
      "paymentCurrencyExchangeRate": 1,
      "paymentCurrencySymbol": "Fr."
    },
    "totalPrice": {
      "basePayoutCurrencyCode": "USD",
      "basePayoutPrice": 206,
      "convenienceFee": 0,
      "currencyCode": "CHF",
      "discount": 0,
      "discountPrice": 199,
      "originalPrice": 199,
      "originalUnitPrice": null,
      "unitPrice": null,
      "vat": 14,
      "voucherDiscount": 0
    }
  }
}