{
  "id": "65dba75e17284af4b30f1402092a1795",
  "price": {
    "totalPaymentPrice": {
      "paymentCurrencyAmount": 3499,
      "paymentCurrencyCode": "CHF",
      "paymentCurrencyExchangeRate": 1,
      "paymentCurrencySymbol": "Fr."
    },
    "totalPrice": {
      "basePayoutCurrencyCode": "USD",
      "basePayoutPrice": 3449,
      "convenienceFee": 0,
      "currencyCode": "CHF",
      "discount": 3500,
      "discountPrice": 3499,
      "originalPrice": 6999,
      "originalUnitPrice": null,
      "unitPrice": null,
      "vat": 250,
      "voucherDiscount": 0
    }
  }
}