{
  "id": "ac6f0a0144854027b437cc30bc9277c2",
  "price": {
    "totalPaymentPrice": {
      "paymentCurrencyAmount": 769900,
      "paymentCurrencyCode": "MXN",
      "paymentCurrencyExchangeRate": 1,
      "paymentCurrencySymbol": "$"
    },
    "totalPrice": {
      "basePayoutCurrencyCode": "USD",
      "basePayoutPrice": 38575,
      "convenienceFee": 0,
      "currencyCode": "MXN",
      "discount": 0,
      "discountPrice": 769900,
      "originalPrice": 769900,
      "originalUnitPrice": null,
      "unitPrice": null,
      "vat": 0,
      "voucherDiscount": 0
    }
  }
}