{
  "id": "5bf5cacc6974434eb623a33a19e28e2b",
  "price": {
    "totalPaymentPrice": {
      "paymentCurrencyAmount": 4199,
      "paymentCurrencyCode": "DKK",
      "paymentCurrencyExchangeRate": 1,
      "paymentCurrencySymbol": "kr."
    },
    "totalPrice": {
      "basePayoutCurrencyCode": "USD",
      "basePayoutPrice": 539,
      "convenienceFee": 0,
      "currencyCode": "DKK",
      "discount": 0,
      "discountPrice": 4199,
      "originalPrice": 4199,
      "originalUnitPrice": null,
      "unitPrice": null,
      "vat": 840,
      "voucherDiscount": 0
    }
  }
}