{
  "id": "8a97a7d4d0e44523b9aa064f457627da",
  "price": {
    "totalPaymentPrice": {
      "paymentCurrencyAmount": 0,
      "paymentCurrencyCode": "IDR",
      "paymentCurrencyExchangeRate": 1,
      "paymentCurrencySymbol": "Rp"
    },
    "totalPrice": {
      "basePayoutCurrencyCode": "USD",
      "basePayoutPrice": 0,
      "convenienceFee": 0,
      "currencyCode": "IDR",
      "discount": 38900000,
      "discountPrice": 0,
      "originalPrice": 38900000,
      "originalUnitPrice": null,
      "unitPrice": null,
      "vat": 0,
      "voucherDiscount": 0
    }
  }
}