{
  "id": "b5849b3701964fc0ac014af72d088769",
  "price": {
    "totalPaymentPrice": {
      "paymentCurrencyAmount": 6060000,
      "paymentCurrencyCode": "IDR",
      "paymentCurrencyExchangeRate": 1,
      "paymentCurrencySymbol": "Rp"
    },
    "totalPrice": {
      "basePayoutCurrencyCode": "USD",
      "basePayoutPrice": 383,
      "convenienceFee": 0,
      "currencyCode": "IDR",
      "discount": 4040000,
      "discountPrice": 6060000,
      "originalPrice": 10100000,
      "originalUnitPrice": null,
      "unitPrice": null,
      "vat": 550900,
      "voucherDiscount": 0
    }
  }
}