{
  "id": "bfdbe8b8e105460eae19c664e51b95cb",
  "price": {
    "totalPaymentPrice": {
      "paymentCurrencyAmount": 2969900,
      "paymentCurrencyCode": "IDR",
      "paymentCurrencyExchangeRate": 1,
      "paymentCurrencySymbol": "Rp"
    },
    "totalPrice": {
      "basePayoutCurrencyCode": "USD",
      "basePayoutPrice": 189,
      "convenienceFee": 0,
      "currencyCode": "IDR",
      "discount": 330000,
      "discountPrice": 2969900,
      "originalPrice": 3299900,
      "originalUnitPrice": null,
      "unitPrice": null,
      "vat": 269900,
      "voucherDiscount": 0
    }
  }
}