{
  "id": "744d2f8fc8f849b68294c6644a2735c8",
  "price": {
    "totalPaymentPrice": {
      "paymentCurrencyAmount": 26000,
      "paymentCurrencyCode": "CNY",
      "paymentCurrencyExchangeRate": 1,
      "paymentCurrencySymbol": "¥"
    },
    "totalPrice": {
      "basePayoutCurrencyCode": "USD",
      "basePayoutPrice": 4015,
      "convenienceFee": 0,
      "currencyCode": "CNY",
      "discount": 0,
      "discountPrice": 26000,
      "originalPrice": 26000,
      "originalUnitPrice": null,
      "unitPrice": null,
      "vat": 0,
      "voucherDiscount": 0
    }
  }
}