{
  "id": "3c7b80f9cfb3468eb1a814513d0413e1",
  "price": {
    "totalPaymentPrice": {
      "paymentCurrencyAmount": 42319,
      "paymentCurrencyCode": "AED",
      "paymentCurrencyExchangeRate": 1,
      "paymentCurrencySymbol": "د.إ"
    },
    "totalPrice": {
      "basePayoutCurrencyCode": "USD",
      "basePayoutPrice": 11523,
      "convenienceFee": 0,
      "currencyCode": "AED",
      "discount": 10580,
      "discountPrice": 42319,
      "originalPrice": 52899,
      "originalUnitPrice": null,
      "unitPrice": null,
      "vat": 0,
      "voucherDiscount": 0
    }
  }
}