{
  "id": "2c519229322f42a5afff5de121f928ed",
  "price": {
    "totalPaymentPrice": {
      "paymentCurrencyAmount": 724,
      "paymentCurrencyCode": "PLN",
      "paymentCurrencyExchangeRate": 1,
      "paymentCurrencySymbol": "zł"
    },
    "totalPrice": {
      "basePayoutCurrencyCode": "USD",
      "basePayoutPrice": 149,
      "convenienceFee": 0,
      "currencyCode": "PLN",
      "discount": 725,
      "discountPrice": 724,
      "originalPrice": 1449,
      "originalUnitPrice": null,
      "unitPrice": null,
      "vat": 135,
      "voucherDiscount": 0
    }
  }
}