{
  "id": "080c18d3c2b342ba95be1fc7e95f6366",
  "price": {
    "totalPaymentPrice": {
      "paymentCurrencyAmount": 3045,
      "paymentCurrencyCode": "AUD",
      "paymentCurrencyExchangeRate": 1,
      "paymentCurrencySymbol": "$"
    },
    "totalPrice": {
      "basePayoutCurrencyCode": "USD",
      "basePayoutPrice": 2119,
      "convenienceFee": 0,
      "currencyCode": "AUD",
      "discount": 0,
      "discountPrice": 3045,
      "originalPrice": 3045,
      "originalUnitPrice": null,
      "unitPrice": null,
      "vat": 277,
      "voucherDiscount": 0
    }
  }
}