{
  "id": "09736850a56a44b38d965112ada6fd95",
  "price": {
    "totalPaymentPrice": {
      "paymentCurrencyAmount": 95000,
      "paymentCurrencyCode": "RUB",
      "paymentCurrencyExchangeRate": 1,
      "paymentCurrencySymbol": "₽"
    },
    "totalPrice": {
      "basePayoutCurrencyCode": "USD",
      "basePayoutPrice": 1059,
      "convenienceFee": 0,
      "currencyCode": "RUB",
      "discount": 0,
      "discountPrice": 95000,
      "originalPrice": 95000,
      "originalUnitPrice": null,
      "unitPrice": null,
      "vat": 15833,
      "voucherDiscount": 0
    }
  }
}