{
  "id": "46a753a7dbc74d34a53137ce1d12651d",
  "price": {
    "totalPaymentPrice": {
      "paymentCurrencyAmount": 1089000,
      "paymentCurrencyCode": "RUB",
      "paymentCurrencyExchangeRate": 1,
      "paymentCurrencySymbol": "₽"
    },
    "totalPrice": {
      "basePayoutCurrencyCode": "USD",
      "basePayoutPrice": 12255,
      "convenienceFee": 0,
      "currencyCode": "RUB",
      "discount": 0,
      "discountPrice": 1089000,
      "originalPrice": 1089000,
      "originalUnitPrice": null,
      "unitPrice": null,
      "vat": 181500,
      "voucherDiscount": 0
    }
  }
}