{
  "id": "58a8a6e7c736477ba451f6fe79bf3d44",
  "price": {
    "totalPaymentPrice": {
      "paymentCurrencyAmount": 1099,
      "paymentCurrencyCode": "BRL",
      "paymentCurrencyExchangeRate": 1,
      "paymentCurrencySymbol": "R$"
    },
    "totalPrice": {
      "basePayoutCurrencyCode": "USD",
      "basePayoutPrice": 221,
      "convenienceFee": 0,
      "currencyCode": "BRL",
      "discount": 0,
      "discountPrice": 1099,
      "originalPrice": 1099,
      "originalUnitPrice": null,
      "unitPrice": null,
      "vat": 0,
      "voucherDiscount": 0
    }
  }
}