{
  "id": "bc1913d78a7d419db8a72e2b7c3733f6",
  "price": {
    "totalPaymentPrice": {
      "paymentCurrencyAmount": 9899,
      "paymentCurrencyCode": "BRL",
      "paymentCurrencyExchangeRate": 1,
      "paymentCurrencySymbol": "R$"
    },
    "totalPrice": {
      "basePayoutCurrencyCode": "USD",
      "basePayoutPrice": 1889,
      "convenienceFee": 0,
      "currencyCode": "BRL",
      "discount": 0,
      "discountPrice": 9899,
      "originalPrice": 9899,
      "originalUnitPrice": null,
      "unitPrice": null,
      "vat": 0,
      "voucherDiscount": 0
    }
  }
}