{
  "id": "beb99af0efd8486880f91472c4ebe928",
  "price": {
    "totalPaymentPrice": {
      "paymentCurrencyAmount": 50652,
      "paymentCurrencyCode": "CZK",
      "paymentCurrencyExchangeRate": 1,
      "paymentCurrencySymbol": "Kč"
    },
    "totalPrice": {
      "basePayoutCurrencyCode": "USD",
      "basePayoutPrice": 1960,
      "convenienceFee": 0,
      "currencyCode": "CZK",
      "discount": 24948,
      "discountPrice": 50652,
      "originalPrice": 75600,
      "originalUnitPrice": null,
      "unitPrice": null,
      "vat": 8791,
      "voucherDiscount": 0
    }
  }
}