{
  "id": "37b456088a484da68368dd86f5ab470a",
  "price": {
    "totalPaymentPrice": {
      "paymentCurrencyAmount": 1890,
      "paymentCurrencyCode": "NOK",
      "paymentCurrencyExchangeRate": 1,
      "paymentCurrencySymbol": "kr"
    },
    "totalPrice": {
      "basePayoutCurrencyCode": "USD",
      "basePayoutPrice": 183,
      "convenienceFee": 0,
      "currencyCode": "NOK",
      "discount": 210,
      "discountPrice": 1890,
      "originalPrice": 2100,
      "originalUnitPrice": null,
      "unitPrice": null,
      "vat": 378,
      "voucherDiscount": 0
    }
  }
}