{
  "id": "9581486276df44cf99f661fe25530158",
  "price": {
    "totalPaymentPrice": {
      "paymentCurrencyAmount": 98696,
      "paymentCurrencyCode": "NOK",
      "paymentCurrencyExchangeRate": 1,
      "paymentCurrencySymbol": "kr"
    },
    "totalPrice": {
      "basePayoutCurrencyCode": "USD",
      "basePayoutPrice": 9540,
      "convenienceFee": 0,
      "currencyCode": "NOK",
      "discount": 42299,
      "discountPrice": 98696,
      "originalPrice": 140995,
      "originalUnitPrice": null,
      "unitPrice": null,
      "vat": 19739,
      "voucherDiscount": 0
    }
  }
}