{
  "id": "f3737de50bd44c0eacc3ed48dcb9d82e",
  "price": {
    "totalPaymentPrice": {
      "paymentCurrencyAmount": 2600,
      "paymentCurrencyCode": "NOK",
      "paymentCurrencyExchangeRate": 1,
      "paymentCurrencySymbol": "kr"
    },
    "totalPrice": {
      "basePayoutCurrencyCode": "USD",
      "basePayoutPrice": 241,
      "convenienceFee": 0,
      "currencyCode": "NOK",
      "discount": 2600,
      "discountPrice": 2600,
      "originalPrice": 5200,
      "originalUnitPrice": null,
      "unitPrice": null,
      "vat": 520,
      "voucherDiscount": 0
    }
  }
}