{
  "id": "aa91594df37a409ca2385f9844f2da53",
  "price": {
    "totalPaymentPrice": {
      "paymentCurrencyAmount": 3299,
      "paymentCurrencyCode": "CAD",
      "paymentCurrencyExchangeRate": 1,
      "paymentCurrencySymbol": "$"
    },
    "totalPrice": {
      "basePayoutCurrencyCode": "USD",
      "basePayoutPrice": 2661,
      "convenienceFee": 0,
      "currencyCode": "CAD",
      "discount": 0,
      "discountPrice": 3299,
      "originalPrice": 3299,
      "originalUnitPrice": null,
      "unitPrice": null,
      "vat": 0,
      "voucherDiscount": 0
    }
  }
}