{
  "id": "8bc48964234345d0a603e30b6b1839ab",
  "price": {
    "totalPaymentPrice": {
      "paymentCurrencyAmount": 440,
      "paymentCurrencyCode": "JPY",
      "paymentCurrencyExchangeRate": 1,
      "paymentCurrencySymbol": "¥"
    },
    "totalPrice": {
      "basePayoutCurrencyCode": "USD",
      "basePayoutPrice": 366,
      "convenienceFee": 0,
      "currencyCode": "JPY",
      "discount": 110,
      "discountPrice": 440,
      "originalPrice": 550,
      "originalUnitPrice": null,
      "unitPrice": null,
      "vat": 40,
      "voucherDiscount": 0
    }
  }
}