{
  "id": "ac5a1130727546f082a63ac7321dbde7",
  "price": {
    "totalPaymentPrice": {
      "paymentCurrencyAmount": 606,
      "paymentCurrencyCode": "JPY",
      "paymentCurrencyExchangeRate": 1,
      "paymentCurrencySymbol": "¥"
    },
    "totalPrice": {
      "basePayoutCurrencyCode": "USD",
      "basePayoutPrice": 499,
      "convenienceFee": 0,
      "currencyCode": "JPY",
      "discount": 0,
      "discountPrice": 606,
      "originalPrice": 606,
      "originalUnitPrice": null,
      "unitPrice": null,
      "vat": 55,
      "voucherDiscount": 0
    }
  }
}