{
  "id": "e321199ce26e4922b296c023806ce1fe",
  "price": {
    "totalPaymentPrice": {
      "paymentCurrencyAmount": 2520,
      "paymentCurrencyCode": "JPY",
      "paymentCurrencyExchangeRate": 1,
      "paymentCurrencySymbol": "¥"
    },
    "totalPrice": {
      "basePayoutCurrencyCode": "USD",
      "basePayoutPrice": 2164,
      "convenienceFee": 0,
      "currencyCode": "JPY",
      "discount": 630,
      "discountPrice": 2520,
      "originalPrice": 3150,
      "originalUnitPrice": null,
      "unitPrice": null,
      "vat": 229,
      "voucherDiscount": 0
    }
  }
}