{
  "id": "a1f38f2d5dc64777a84cd44b7d8e7f64",
  "price": {
    "totalPaymentPrice": {
      "paymentCurrencyAmount": 6200,
      "paymentCurrencyCode": "KRW",
      "paymentCurrencyExchangeRate": 1,
      "paymentCurrencySymbol": "₩"
    },
    "totalPrice": {
      "basePayoutCurrencyCode": "USD",
      "basePayoutPrice": 508,
      "convenienceFee": 0,
      "currencyCode": "KRW",
      "discount": 9300,
      "discountPrice": 6200,
      "originalPrice": 15500,
      "originalUnitPrice": null,
      "unitPrice": null,
      "vat": 560,
      "voucherDiscount": 0
    }
  }
}